qgis-stubs/_3d.pyi
qgis-stubs/__init__.pyi
qgis-stubs/analysis.pyi
qgis-stubs/gui.pyi
qgis-stubs/server.pyi
qgis-stubs/core/__init__.pyi
qgis-stubs/core/_additions.pyi
qgis-stubs/core/_context_managers.pyi
qgis-stubs/processing/__init__.pyi
qgis-stubs/processing/algfactory.pyi
qgis_stubs-0.2.0.post1.dist-info/LICENSE
qgis_stubs-0.2.0.post1.dist-info/METADATA
qgis_stubs-0.2.0.post1.dist-info/WHEEL
qgis_stubs-0.2.0.post1.dist-info/top_level.txt
qgis_stubs-0.2.0.post1.dist-info/RECORD
