Metadata-Version: 2.1
Name: qgis-stubs
Version: 0.2.0.post1
Summary: PEP561 type stubs for PyQGIS
Home-page: https://github.com/leonhard-s/qgis-stubs
Author: Leonhard S.
Maintainer-email: leonhard-sei@outlook.com
Classifier: Development Status :: 3 - Alpha
Classifier: License :: OSI Approved :: GNU General Public License v3 (GPLv3)
Classifier: Intended Audience :: Developers
Classifier: Programming Language :: Python :: 3
Classifier: Topic :: Software Development
Requires-Python: >= 3.6
License-File: LICENSE
